{
  "todos": [
    {
      "id": 1,
      "content": "Chakra UIをインストールする",
      "done": "done"
    },
    {
      "id": 2,
      "content": "JSON Server仮のAPIを作成する",
      "done": "done"
    },
    {
      "id": 1,
      "content": "Chakra UIをインストールする",
      "done": false
    },
    {
      "content": "useRefの使い方をを確認する",
      "id": "01FV4B8CY0S4EZ35N74SFBN2M9",
      "done": "done"
    },
    {
      "content": "mathhhhhhh",
      "id": "01FVA4WV2DVHT6JT8292KTA0KS",
      "done": false
    }
  ]
}